libvirt_instance/__init__.py
libvirt_instance/cli.py
libvirt_instance/config.py
libvirt_instance/domain-presets/headless-server-aarch64.xml
libvirt_instance/domain-presets/headless-server-x86_64.xml
libvirt_instance/domain.py
libvirt_instance/output.py
libvirt_instance/py.typed
libvirt_instance/seed_image.py
libvirt_instance/util.py
libvirt_instance-0.1.7.dist-info/LICENSE
libvirt_instance-0.1.7.dist-info/METADATA
libvirt_instance-0.1.7.dist-info/WHEEL
libvirt_instance-0.1.7.dist-info/entry_points.txt
libvirt_instance-0.1.7.dist-info/RECORD
