Metadata-Version: 2.1
Name: libvirt-instance
Version: 0.1.7
Summary: VM provisioning and management tool
Home-page: https://github.com/node13h/libvirt-instance
License: MIT
Author: Sergej Alikov
Author-email: sergej@alikov.com
Requires-Python: >=3.10,<4.0
Classifier: License :: OSI Approved :: MIT License
Classifier: Programming Language :: Python :: 3
Classifier: Programming Language :: Python :: 3.10
Classifier: Programming Language :: Python :: 3.11
Classifier: Programming Language :: Python :: 3.12
Requires-Dist: PyYAML (>=6.0.1,<7.0.0)
Requires-Dist: libvirt-python (>=8.0)
Requires-Dist: pycdlib (>=1.14.0,<2.0.0)
Project-URL: Repository, https://github.com/node13h/libvirt-instance
